{
  "version": "1.1.1",
  "windows": {
    "main": {
      "main": true,
      "url": "app://editor/index.html",
      "windowType": "dockable",
      "x": -8,
      "y": -8,
      "width": 1382,
      "height": 744,
      "layout": {
        "children": [
          {
            "children": [
              {
                "active": 0,
                "children": [
                  "hierarchy"
                ],
                "height": 268,
                "type": "panel",
                "width": 204
              },
              {
                "active": 0,
                "children": [
                  "assets"
                ],
                "height": 345,
                "type": "panel",
                "width": 204
              }
            ],
            "height": 616,
            "type": "dock-v",
            "width": 204
          },
          {
            "children": [
              {
                "children": [
                  {
                    "active": 0,
                    "children": [
                      "scene"
                    ],
                    "height": 387,
                    "type": "panel",
                    "width": 617.984375
                  },
                  {
                    "active": 0,
                    "children": [
                      "node-library"
                    ],
                    "height": 387,
                    "type": "panel",
                    "width": 224.984375
                  }
                ],
                "height": 387,
                "type": "dock-h",
                "width": 845.984375
              },
              {
                "active": 0,
                "children": [
                  "console",
                  "timeline"
                ],
                "height": 226,
                "type": "panel",
                "width": 845.984375
              }
            ],
            "height": 616,
            "type": "dock-v",
            "width": 845.984375
          },
          {
            "active": 0,
            "children": [
              "inspector"
            ],
            "height": 616,
            "type": "panel",
            "width": 304
          }
        ],
        "type": "dock-h"
      },
      "panels": [
        "node-library",
        "console",
        "inspector",
        "hierarchy",
        "assets",
        "scene",
        "timeline"
      ]
    }
  },
  "panels": {
    "project-settings": {
      "x": 385,
      "y": 84,
      "width": 600,
      "height": 565
    },
    "builder": {
      "x": 450,
      "y": 10,
      "width": 516,
      "height": 728
    }
  }
}